pybacktestchain/__init__.py
pybacktestchain/blockchain.py
pybacktestchain/broker.py
pybacktestchain/data_module.py
pybacktestchain/pybacktestchain.py
pybacktestchain/utils.py
pybacktestchain-0.2.1.dist-info/LICENSE
pybacktestchain-0.2.1.dist-info/METADATA
pybacktestchain-0.2.1.dist-info/WHEEL
pybacktestchain-0.2.1.dist-info/RECORD
